luma/core/__init__.py
luma/core/ansi_color.py
luma/core/bitmap_font.py
luma/core/cmdline.py
luma/core/const.py
luma/core/device.py
luma/core/error.py
luma/core/framebuffer.py
luma/core/image_composition.py
luma/core/lib.py
luma/core/mixin.py
luma/core/render.py
luma/core/sprite_system.py
luma/core/threadpool.py
luma/core/util.py
luma/core/virtual.py
luma/core/interface/__init__.py
luma/core/interface/parallel.py
luma/core/interface/serial.py
luma/core/legacy/__init__.py
luma/core/legacy/font.py
luma.core-2.4.2.dist-info/LICENSE.rst
luma.core-2.4.2.dist-info/METADATA
luma.core-2.4.2.dist-info/WHEEL
luma.core-2.4.2.dist-info/top_level.txt
luma.core-2.4.2.dist-info/RECORD
