Metadata-Version: 2.1
Name: luma.core
Version: 2.4.2
Summary: A component library to support SBC display drivers
Home-page: https://github.com/rm-hull/luma.core
Author: Richard Hull
Author-email: richard.hull@destructuring-bind.org
License: MIT
Keywords: raspberry,orange,banana,pi,rpi,opi,sbc,oled,lcd,led,display,screen,spi,i2c,ftdi,usb
Classifier: License :: OSI Approved :: MIT License
Classifier: Development Status :: 5 - Production/Stable
Classifier: Intended Audience :: Education
Classifier: Intended Audience :: Developers
Classifier: Topic :: Education
Classifier: Topic :: System :: Hardware
Classifier: Topic :: System :: Hardware :: Hardware Drivers
Classifier: Programming Language :: Python :: 3
Classifier: Programming Language :: Python :: 3.7
Classifier: Programming Language :: Python :: 3.8
Classifier: Programming Language :: Python :: 3.9
Classifier: Programming Language :: Python :: 3.10
Classifier: Programming Language :: Python :: 3.11
Classifier: Programming Language :: Python :: 3.12
Requires-Python: <4,>=3.7
License-File: LICENSE.rst
Requires-Dist: pillow>=9.2.0
Requires-Dist: smbus2
Requires-Dist: pyftdi
Requires-Dist: cbor2
Requires-Dist: RPI.GPIO; platform_system == "Linux"
Requires-Dist: spidev; platform_system == "Linux"
Provides-Extra: docs
Requires-Dist: sphinx>=1.5.1; extra == "docs"
Requires-Dist: sphinx-rtd-theme; extra == "docs"
Provides-Extra: qa
Requires-Dist: flake8; extra == "qa"
Requires-Dist: rstcheck; extra == "qa"
Provides-Extra: test
Requires-Dist: pytest; extra == "test"
Requires-Dist: pytest-cov; extra == "test"
Requires-Dist: pytest-timeout; extra == "test"
Requires-Dist: pytest-watch; extra == "test"
